django_tenant_options/__init__.py
django_tenant_options/admin.py
django_tenant_options/app_settings.py
django_tenant_options/apps.py
django_tenant_options/checks.py
django_tenant_options/choices.py
django_tenant_options/exceptions.py
django_tenant_options/form_fields.py
django_tenant_options/forms.py
django_tenant_options/helpers.py
django_tenant_options/models.py
django_tenant_options/urls.py
django_tenant_options/views.py
django_tenant_options/management/__init__.py
django_tenant_options/management/commands/__init__.py
django_tenant_options/management/commands/listoptions.py
django_tenant_options/management/commands/maketriggers.py
django_tenant_options/management/commands/removetriggers.py
django_tenant_options/management/commands/syncoptions.py
django_tenant_options/migrations/__init__.py
django_tenant_options-2024.12.3.dist-info/LICENSE
django_tenant_options-2024.12.3.dist-info/METADATA
django_tenant_options-2024.12.3.dist-info/WHEEL
django_tenant_options-2024.12.3.dist-info/top_level.txt
django_tenant_options-2024.12.3.dist-info/RECORD
