Metadata-Version: 2.1
Name: django-tenant-options
Version: 2024.12.3
Summary: Empowering Your SaaS Tenants with Custom Options and Sane Defaults
Author-email: Jack Linke <jacklinke@gmail.com>
License: MIT
Project-URL: Homepage, https://github.com/OmenApps/django-tenant-options
Project-URL: Repository, https://github.com/OmenApps/django-tenant-options
Project-URL: Documentation, https://django-tenant-options.readthedocs.io
Project-URL: Changelog, https://github.com/OmenApps/django-tenant-options/releases
Classifier: Environment :: Web Environment
Classifier: Framework :: Django
Classifier: Framework :: Django :: 4.2
Classifier: Framework :: Django :: 5.0
Classifier: Framework :: Django :: 5.1
Classifier: Development Status :: 4 - Beta
Classifier: Intended Audience :: Developers
Classifier: License :: OSI Approved :: MIT License
Classifier: Operating System :: OS Independent
Classifier: Programming Language :: Python
Classifier: Programming Language :: Python :: 3
Classifier: Programming Language :: Python :: 3.10
Classifier: Programming Language :: Python :: 3.11
Classifier: Programming Language :: Python :: 3.12
Classifier: Programming Language :: Python :: 3.13
Classifier: Topic :: Internet :: WWW/HTTP
Classifier: Topic :: Internet :: WWW/HTTP :: Dynamic Content
Classifier: Topic :: Software Development :: Libraries :: Python Modules
Requires-Python: <4.0,>=3.10
License-File: LICENSE
Requires-Dist: django>=4.2.15
Requires-Dist: click~=8.1
